partition_networkx/__init__.py
partition_networkx/partition_networkx.py
partition_networkx-0.0.2.dist-info/LICENSE
partition_networkx-0.0.2.dist-info/METADATA
partition_networkx-0.0.2.dist-info/WHEEL
partition_networkx-0.0.2.dist-info/top_level.txt
partition_networkx-0.0.2.dist-info/RECORD
