Metadata-Version: 2.1
Name: partition-networkx
Version: 0.0.2
Summary: Adds ensemble clustering (ecg) and graph-aware measures (gam) to networkx.
Home-page: https://github.com/ftheberge/graph-partition-and-measures
Author: Valérie Poulin and François Théberge
Author-email: theberge@ieee.org
License: MIT
Classifier: Development Status :: 4 - Beta
Classifier: License :: OSI Approved :: MIT License
Classifier: Programming Language :: Python
Classifier: Programming Language :: Python :: 3
Classifier: Topic :: Scientific/Engineering
Classifier: Topic :: Software Development :: Libraries :: Python Modules
Classifier: Intended Audience :: Science/Research
Requires-Python: >=3.9
License-File: LICENSE
Requires-Dist: networkx
Requires-Dist: python-louvain
Requires-Dist: numpy
